setup.py
libpcapy/__init__.py
libpcapy/capture.py
libpcapy/pcap_structures.py
libpcapy.egg-info/PKG-INFO
libpcapy.egg-info/SOURCES.txt
libpcapy.egg-info/dependency_links.txt
libpcapy.egg-info/top_level.txt