Metadata-Version: 1.0
Name: libpcapy
Version: 0.2.0
Summary: Python library to use libpcap using ctypes
Home-page: https://github.com/alagoa/libpcapy
Author: Pedro Alagoa
Author-email: alagoa.pedro@ua.pt
License: MIT
Platform: UNKNOWN
